CHANGELOG.md
LICENSE
MANIFEST.in
README.md
setup.cfg
setup.py
pip_services_runtime/AbstractComponent.py
pip_services_runtime/ComponentSet.py
pip_services_runtime/IAddon.py
pip_services_runtime/IBootConfig.py
pip_services_runtime/IBusinessLogic.py
pip_services_runtime/ICache.py
pip_services_runtime/IClient.py
pip_services_runtime/IComponent.py
pip_services_runtime/IComponentFactory.py
pip_services_runtime/IController.py
pip_services_runtime/ICounters.py
pip_services_runtime/IDecorator.py
pip_services_runtime/IDiscovery.py
pip_services_runtime/ILogger.py
pip_services_runtime/IPersistence.py
pip_services_runtime/IService.py
pip_services_runtime/ITiming.py
pip_services_runtime/LogLevel.py
pip_services_runtime/State.py
pip_services_runtime/__init__.py
pip_services_runtime.egg-info/PKG-INFO
pip_services_runtime.egg-info/SOURCES.txt
pip_services_runtime.egg-info/dependency_links.txt
pip_services_runtime.egg-info/requires.txt
pip_services_runtime.egg-info/top_level.txt
pip_services_runtime.egg-info/zip-safe
pip_services_runtime/addons/AbstractAddon.py
pip_services_runtime/addons/__init__.py
pip_services_runtime/boot/AbstractBootConfig.py
pip_services_runtime/boot/FileBootConfig.py
pip_services_runtime/boot/__init__.py
pip_services_runtime/build/Builder.py
pip_services_runtime/build/ComponentFactory.py
pip_services_runtime/build/DefaultFactory.py
pip_services_runtime/build/FactoryRegistration.py
pip_services_runtime/build/__init__.py
pip_services_runtime/cache/AbstractCache.py
pip_services_runtime/cache/CacheEntry.py
pip_services_runtime/cache/MemoryCache.py
pip_services_runtime/cache/NullCache.py
pip_services_runtime/cache/__init__.py
pip_services_runtime/clients/AbstractClient.py
pip_services_runtime/clients/DirectClient.py
pip_services_runtime/clients/RestClient.py
pip_services_runtime/clients/__init__.py
pip_services_runtime/commands/Command.py
pip_services_runtime/commands/CommandSet.py
pip_services_runtime/commands/ICommand.py
pip_services_runtime/commands/ICommandIntercepter.py
pip_services_runtime/commands/InterceptedCommand.py
pip_services_runtime/commands/TimingIntercepter.py
pip_services_runtime/commands/TracingIntercepter.py
pip_services_runtime/commands/__init__.py
pip_services_runtime/config/Category.py
